pyglicko2/__init__.py
pyglicko2-0.0.1a2.dist-info/METADATA
pyglicko2-0.0.1a2.dist-info/WHEEL
pyglicko2-0.0.1a2.dist-info/licenses/LICENSE
pyglicko2-0.0.1a2.dist-info/RECORD
