Metadata-Version: 2.3
Name: pyglicko2
Version: 0.0.1a2
Summary: Python implementation of the Glicko-2 system
Author-email: Jingyang Wang <wangjy2010@126.com>
Maintainer-email: Jingyang Wang <wangjy2010@126.com>
License-File: LICENSE
Keywords: chess,rating-system
Classifier: Development Status :: 3 - Alpha
Classifier: License :: OSI Approved :: MIT License
Classifier: Operating System :: OS Independent
Classifier: Programming Language :: Python :: 3
Classifier: Programming Language :: Python :: 3.8
Classifier: Programming Language :: Python :: 3.9
Classifier: Programming Language :: Python :: 3.10
Classifier: Programming Language :: Python :: 3.11
Classifier: Programming Language :: Python :: 3.12
Requires-Python: >=3.8
